CHANGELOG.md
LICENSE
MANIFEST.in
README.md
requirements.txt
setup.cfg
setup.py
ecmcli/__init__.py
ecmcli/api.py
ecmcli/mac.db
ecmcli/main.py
ecmcli/ui.py
ecmcli.egg-info/PKG-INFO
ecmcli.egg-info/SOURCES.txt
ecmcli.egg-info/dependency_links.txt
ecmcli.egg-info/entry_points.txt
ecmcli.egg-info/requires.txt
ecmcli.egg-info/top_level.txt
ecmcli/commands/__init__.py
ecmcli/commands/accounts.py
ecmcli/commands/activity_log.py
ecmcli/commands/alerts.py
ecmcli/commands/apps.py
ecmcli/commands/authorizations.py
ecmcli/commands/base.py
ecmcli/commands/clients.py
ecmcli/commands/features.py
ecmcli/commands/firmware.py
ecmcli/commands/groups.py
ecmcli/commands/login.py
ecmcli/commands/logs.py
ecmcli/commands/messages.py
ecmcli/commands/netflow.py
ecmcli/commands/remote.py
ecmcli/commands/routers.py
ecmcli/commands/shell.py
ecmcli/commands/shtools.py
ecmcli/commands/tos.py
ecmcli/commands/trace.py
ecmcli/commands/users.py
ecmcli/commands/wanrate.py
ecmcli/commands/wifi.py
test/__init__.py
test/api_glob.py
test/reboot.py
test/remote_config.py