Metadata-Version: 1.1
Name: ecmcli
Version: 10
Summary: Command Line Interface for Cradlepoint ECM (e.g. NCM)
Home-page: https://github.com/mayfield/ecmcli/
Author: Justin Mayfield
Author-email: tooker@gmail.com
License: MIT
Platform: UNKNOWN
Classifier: Development Status :: 4 - Beta
Classifier: Intended Audience :: Developers
Classifier: License :: OSI Approved :: MIT License
Classifier: Operating System :: OS Independent
Classifier: Programming Language :: Python
Classifier: Programming Language :: Python :: 3.4
Classifier: Programming Language :: Python :: 3.5
Classifier: Programming Language :: Python :: 3.6
Classifier: Programming Language :: Python :: 3.7
